MANIFEST.in
README.md
setup.cfg
setup.py
infdata/__init__.py
infdata/__main__.py
infdata/cli.py
infdata/ping.py
infdata/settings.py
infdata/utils.py
infdata/commands/__init__.py
infdata/commands/base.py
infdata/commands/init.py
infdata/commands/list.py
infdata/commands/login.py
infdata/commands/pull.py
infdata/commands/push.py
infdata/commands/run.py
infdata/commands/tasks.py
infdata/commands/which.py
tasks/__init__.py
tasks/futureoflife_example.py
tasks/slashdot_example.py
tasks/wechat.py
tests/test_cli.py
tests/test_utils.py
tests/commands/test_init.py
tests/testdata/records.json